DijkstraPathfinder/__init__.py
DijkstraPathfinder/Algorithms/__init__.py
DijkstraPathfinder/Algorithms/Dijkstra/__init__.py
DijkstraPathfinder/Algorithms/Dijkstra/Bindings/__init__.py
DijkstraPathfinder/Algorithms/Dijkstra/Bindings/dijkstra_bindings.c
DijkstraPathfinder/Algorithms/Dijkstra/Bindings/dijkstra_bindings.py
DijkstraPathfinder/Algorithms/Dijkstra/Implementation/__init__.py
DijkstraPathfinder/Algorithms/Dijkstra/Implementation/dijkstra.c
DijkstraPathfinder/Algorithms/Dijkstra/Implementation/dijkstra.h
DijkstraPathfinder/DataStructures/__init__.py
DijkstraPathfinder/DataStructures/Graph/__init__.py
DijkstraPathfinder/DataStructures/Graph/graph.c
DijkstraPathfinder/DataStructures/Graph/graph.h
DijkstraPathfinder/DataStructures/Heap/__init__.py
DijkstraPathfinder/DataStructures/Heap/heap.c
DijkstraPathfinder/DataStructures/Heap/heap.h
dijkstrapathfinder-1.0.6.dist-info/LICENSE
dijkstrapathfinder-1.0.6.dist-info/METADATA
dijkstrapathfinder-1.0.6.dist-info/WHEEL
dijkstrapathfinder-1.0.6.dist-info/top_level.txt
dijkstrapathfinder-1.0.6.dist-info/RECORD
